{
  "fields": {
    "last_mod": "2014-11-08T23:21:53.188Z",
    "concepts": [
      "0ldu1aud",
      "0wxbs715",
      "4mger90x",
      "6zgu0pb6",
      "75bzyvan",
      "7cedq6br",
      "9qd1a8d6",
      "cj7urqv5",
      "cja1np7y",
      "cqpveand",
      "gvp31pbp",
      "hkrsnv1p",
      "i9mo2e09",
      "iszv8c6h",
      "jo8tm547",
      "k4imou8p",
      "lu25c8st",
      "mnj2e4z2",
      "qwj4lbj9",
      "uefstju4",
      "veollwsb",
      "wahfxtxd",
      "ygqeubhx",
      "zd073egx",
      "zlk11edy",
      "zugf8116"
    ],
    "dependencies": [
      "0ldu1audcqpveand",
      "0wxbs7150ldu1aud",
      "0wxbs71575bzyvan",
      "4mger90x6zgu0pb6",
      "4mger90x7cedq6br",
      "4mger90xcqpveand",
      "4mger90xjo8tm547",
      "4mger90xlu25c8st",
      "75bzyvancqpveand",
      "7cedq6brlu25c8st",
      "9qd1a8d60ldu1aud",
      "9qd1a8d6ygqeubhx",
      "cj7urqv5gvp31pbp",
      "cja1np7ywahfxtxd",
      "cja1np7yzd073egx",
      "cqpveand6zgu0pb6",
      "gvp31pbpveollwsb",
      "hkrsnv1pcqpveand",
      "i9mo2e09cj7urqv5",
      "i9mo2e09veollwsb",
      "iszv8c6hhkrsnv1p",
      "jo8tm547zugf8116",
      "k4imou8pygqeubhx",
      "k4imou8pzugf8116",
      "mnj2e4z2cqpveand",
      "mnj2e4z2hkrsnv1p",
      "mnj2e4z2iszv8c6h",
      "mnj2e4z2zugf8116",
      "uefstju40ldu1aud",
      "uefstju475bzyvan",
      "uefstju4wahfxtxd",
      "uefstju4zd073egx",
      "uefstju4zlk11edy",
      "wahfxtxd0wxbs715",
      "wahfxtxd9qd1a8d6",
      "wahfxtxdk4imou8p",
      "ygqeubhxcqpveand",
      "zd073egx0ldu1aud",
      "zd073egxhkrsnv1p",
      "zd073egxygqeubhx",
      "zlk11edyqwj4lbj9"
    ],
    "title": "Symbolic AI"
  },
  "model": "graph.graph",
  "pk": "nwxwdge9"
}
